Metadata-Version: 1.1
Name: smallrnaseq
Version: 0.6.0
Summary: Package for short RNA-seq analysis
Home-page: https://github.com/dmnfarrell/smallrnaseq
Author: Damien Farrell
Author-email: farrell.damien@gmail.com
License: GPL v3
Keywords: rna,sequencing,mirdeep2,biology,scientific
Platform: UNKNOWN
Classifier: Operating System :: OS Independent
Classifier: Programming Language :: Python :: 3.4
Classifier: Programming Language :: Python :: 2.7
Classifier: Operating System :: MacOS :: MacOS X
Classifier: Operating System :: Microsoft :: Windows
Classifier: Operating System :: POSIX
Classifier: License :: OSI Approved :: Apache Software License
Classifier: Development Status :: 4 - Beta
Classifier: Intended Audience :: Science/Research
